{
    "data": [
        {
            "lang": "en",
            "public_metrics": {
                "retweet_count": 0,
                "reply_count": 0,
                "like_count": 0,
                "quote_count": 0
            },
            "id": "1466750729406795776",
            "possibly_sensitive": false,
            "text": "Movie Review 4/5 Stars No Time to\u00a0Die https://t.co/xIIwTH4Dk7",
            "author_id": "164580069",
            "created_at": "2021-12-03T12:46:39.000Z"
        },
        {
            "lang": "en",
            "public_metrics": {
                "retweet_count": 0,
                "reply_count": 2,
                "like_count": 5,
                "quote_count": 0
            },
            "id": "1466750671726780430",
            "possibly_sensitive": false,
            "text": "34 - Casino Royale (Nov 2006)\n47 - No Time To Die (Sept 2021)\n\nI wonder if Bond 26 will be out before I'm 60. https://t.co/FXQ0XvF4Jh",
            "author_id": "1397420517527887872",
            "created_at": "2021-12-03T12:46:25.000Z"
        },
        {
            "lang": "en",
            "public_metrics": {
                "retweet_count": 0,
                "reply_count": 0,
                "like_count": 0,
                "quote_count": 0
            },
            "id": "1466750091511828480",
            "possibly_sensitive": false,
            "text": "My prediction\nBest Stunts For The Winner: #NoTimeToDie \n#HCAFilmAwards https://t.co/3bxhQNkVGy",
            "author_id": "1443971475149516800",
            "created_at": "2021-12-03T12:44:07.000Z"
        },
        {
            "lang": "en",
            "public_metrics": {
                "retweet_count": 0,
                "reply_count": 0,
                "like_count": 0,
                "quote_count": 0
            },
            "id": "1466749799823204358",
            "possibly_sensitive": false,
            "text": "My eyes opened, I am breathing. It's #FridayMorning Ya baaby. College football conference championships and going to see No Time to Die w my youngest son. Life is good.",
            "author_id": "1451769803727769603",
            "created_at": "2021-12-03T12:42:57.000Z"
        },
        {
            "lang": "en",
            "public_metrics": {
                "retweet_count": 1,
                "reply_count": 1,
                "like_count": 1,
                "quote_count": 0
            },
            "id": "1466747926990962691",
            "possibly_sensitive": false,
            "text": "Finally seeing No Time To Die\n\nIt\u2019s all good @Conor_Meechan you can return ma phone calls now\u2026",
            "author_id": "788096857515884544",
            "created_at": "2021-12-03T12:35:31.000Z"
        },
        {
            "lang": "en",
            "public_metrics": {
                "retweet_count": 3,
                "reply_count": 0,
                "like_count": 8,
                "quote_count": 0
            },
            "id": "1466747797068210180",
            "possibly_sensitive": true,
            "text": "Ana de Armas \nN*p Slip \ud83d\udd25\n\n#notimetodie \n#GoodEvening \nhttps://t.co/NLqhu1EJEf",
            "author_id": "1423977988199120899",
            "created_at": "2021-12-03T12:35:00.000Z"
        },
        {
            "lang": "en",
            "public_metrics": {
                "retweet_count": 0,
                "reply_count": 0,
                "like_count": 0,
                "quote_count": 0
            },
            "id": "1466746252998049792",
            "possibly_sensitive": false,
            "text": "the mood is to forget about lessons and go for a walk with friends... fuck, I don't have anyone\n#NoTimeToDie #Friends #friendshib #FridayMorning #fridaynightfunkin #sorrynotsorry #Spotify",
            "author_id": "1056080199526150144",
            "created_at": "2021-12-03T12:28:52.000Z"
        },
        {
            "lang": "en",
            "public_metrics": {
                "retweet_count": 0,
                "reply_count": 0,
                "like_count": 0,
                "quote_count": 0
            },
            "id": "1466745778139922432",
            "possibly_sensitive": false,
            "text": "Imma close down to nobody and no time to die . https://t.co/3gLvSA5DL6",
            "author_id": "1173962027540373504",
            "created_at": "2021-12-03T12:26:58.000Z"
        },
        {
            "lang": "en",
            "public_metrics": {
                "retweet_count": 0,
                "reply_count": 0,
                "like_count": 1,
                "quote_count": 0
            },
            "id": "1466744660534042628",
            "possibly_sensitive": false,
            "text": "Is no time to die just a fast and the furious movie? I mean it has magnets and it includes family.",
            "author_id": "240461439",
            "created_at": "2021-12-03T12:22:32.000Z"
        },
        {
            "lang": "en",
            "public_metrics": {
                "retweet_count": 0,
                "reply_count": 0,
                "like_count": 1,
                "quote_count": 0
            },
            "id": "1466744521602052100",
            "possibly_sensitive": false,
            "text": "I haven\u2019t seen No Time To Die yet but I\u2019m listening to Hans Zimmer\u2019s \u2018Final Ascent\u2019 &amp; feeling it soar. \n\nI can\u2019t imagine a person who listens to this music which encapsulates Bond &amp; \ud83c\uddec\ud83c\udde7 then thinks our current Government are anything but classic villains",
            "author_id": "363218873",
            "created_at": "2021-12-03T12:21:59.000Z"
        },
        {
            "lang": "en",
            "public_metrics": {
                "retweet_count": 0,
                "reply_count": 0,
                "like_count": 0,
                "quote_count": 0
            },
            "id": "1466744508855590920",
            "possibly_sensitive": false,
            "text": "Bond Movies to Watch Instead of No Time to\u00a0Die https://t.co/AscBRc82gL",
            "author_id": "1181834871875858432",
            "created_at": "2021-12-03T12:21:56.000Z"
        },
        {
            "lang": "en",
            "public_metrics": {
                "retweet_count": 0,
                "reply_count": 1,
                "like_count": 1,
                "quote_count": 0
            },
            "id": "1466743229471072258",
            "possibly_sensitive": false,
            "text": "wow ok turns out No Time To Die is actually just metal gear:\n\n\u2705 cool stealth shit\n\u2705 nanomachines\n\u2705 bad dialogue\n\u2705 foxdie\n\u2705 infiltrating island base\n\u2705 ladder\n\u2705 love blooming on battlefield\n\u2754 post credits scene revealing the bad guy is potus (didn\u2019t stay to find out)",
            "author_id": "16878915",
            "created_at": "2021-12-03T12:16:51.000Z"
        },
        {
            "lang": "en",
            "public_metrics": {
                "retweet_count": 0,
                "reply_count": 0,
                "like_count": 0,
                "quote_count": 0
            },
            "id": "1466741632112513025",
            "possibly_sensitive": false,
            "text": "Just finished No Time To Die.\n\nNow, I wanna wear a suit and go around asking for shaken vodka martinis.",
            "author_id": "223056988",
            "created_at": "2021-12-03T12:10:30.000Z"
        },
        {
            "lang": "en",
            "public_metrics": {
                "retweet_count": 2,
                "reply_count": 0,
                "like_count": 20,
                "quote_count": 0
            },
            "id": "1466741464373907457",
            "possibly_sensitive": false,
            "text": "Cuba sequence inspired poster art for No Time To Die by @bartnikp23 https://t.co/veuGYzyAjG",
            "author_id": "1209394210010488832",
            "created_at": "2021-12-03T12:09:50.000Z"
        },
        {
            "lang": "en",
            "public_metrics": {
                "retweet_count": 1,
                "reply_count": 0,
                "like_count": 11,
                "quote_count": 1
            },
            "id": "1466741113163857927",
            "possibly_sensitive": false,
            "text": "MOVIE FRIDAY: NO TIME TO DIE https://t.co/4gUrsa8cB5 via @YouTube",
            "author_id": "4292769747",
            "created_at": "2021-12-03T12:08:26.000Z"
        },
        {
            "lang": "en",
            "public_metrics": {
                "retweet_count": 0,
                "reply_count": 1,
                "like_count": 2,
                "quote_count": 0
            },
            "id": "1466740750583046150",
            "possibly_sensitive": false,
            "text": "Both sad and happy to hear that @007\u2019s No Time To Die is now available in the black underground torrents world.\n\nThis can potentially mean the start of the end for income from the movie. \n\nIn wake of December 12 Blu-Ray release.",
            "author_id": "25475608",
            "geo": {
                "place_id": "82779978c58253a6"
            },
            "created_at": "2021-12-03T12:07:00.000Z"
        },
        {
            "lang": "en",
            "public_metrics": {
                "retweet_count": 6,
                "reply_count": 0,
                "like_count": 33,
                "quote_count": 0
            },
            "id": "1466740192954433541",
            "possibly_sensitive": false,
            "text": "THE TOP 5 FILMS IN THE UK &amp; IRELAND THIS WEEK:\n \n1 - #HouseOfGucci  \n2 - #Ghostbusters: Afterlife \n3 - #Encanto \n4 - #Eternals\n5 - #NoTimeToDie https://t.co/Ma1aqm14oK",
            "author_id": "253294652",
            "created_at": "2021-12-03T12:04:47.000Z"
        },
        {
            "lang": "en",
            "public_metrics": {
                "retweet_count": 0,
                "reply_count": 0,
                "like_count": 0,
                "quote_count": 0
            },
            "id": "1466739711163224070",
            "possibly_sensitive": false,
            "text": "The latest All in 1! https://t.co/tpoXG0nY1I #5things #notimetodie",
            "author_id": "2789268278",
            "created_at": "2021-12-03T12:02:52.000Z"
        },
        {
            "lang": "en",
            "public_metrics": {
                "retweet_count": 0,
                "reply_count": 1,
                "like_count": 3,
                "quote_count": 0
            },
            "id": "1466739169691009028",
            "possibly_sensitive": false,
            "text": "Is anyone here into James Bond??? No Time To Die sure was somethin",
            "author_id": "15316577",
            "created_at": "2021-12-03T12:00:43.000Z"
        },
        {
            "lang": "en",
            "public_metrics": {
                "retweet_count": 1,
                "reply_count": 0,
                "like_count": 1,
                "quote_count": 0
            },
            "id": "1466738995665137670",
            "possibly_sensitive": false,
            "text": "\u2018No Time To Die\u2019 opens December 15 in Philippine Cinemas https://t.co/zzqxe5s3Ex\n#NoTimeToDie",
            "author_id": "387558105",
            "created_at": "2021-12-03T12:00:01.000Z"
        },
        {
            "lang": "en",
            "public_metrics": {
                "retweet_count": 4,
                "reply_count": 3,
                "like_count": 46,
                "quote_count": 0
            },
            "id": "1466738381845639169",
            "possibly_sensitive": false,
            "text": "Finally watched No Time To Die and bro \ud83d\ude2d https://t.co/Cokv9NI0RY",
            "author_id": "1071854361607897088",
            "created_at": "2021-12-03T11:57:35.000Z"
        },
        {
            "lang": "en",
            "public_metrics": {
                "retweet_count": 0,
                "reply_count": 0,
                "like_count": 0,
                "quote_count": 0
            },
            "id": "1466737154940608513",
            "possibly_sensitive": false,
            "text": "the women in no time to die are so hot\ud83d\ude2d\ud83d\ude2d\ud83d\ude2d\ud83d\ude2d\ud83d\ude2d\ud83d\ude2d",
            "author_id": "1254426376209219584",
            "created_at": "2021-12-03T11:52:43.000Z"
        },
        {
            "lang": "en",
            "public_metrics": {
                "retweet_count": 2,
                "reply_count": 1,
                "like_count": 17,
                "quote_count": 1
            },
            "id": "1466735563718168586",
            "possibly_sensitive": false,
            "text": "#NoTimeToDie DVD - 2-Disc Collector's Edition coming soon on 007Store #Bond25 #\u30ce\u30fc\u30bf\u30a4\u30e0\u30c8\u30a5\u30c0\u30a4 #JamesBond https://t.co/j11AA3UHzL",
            "author_id": "416955235",
            "created_at": "2021-12-03T11:46:23.000Z"
        },
        {
            "lang": "en",
            "public_metrics": {
                "retweet_count": 0,
                "reply_count": 1,
                "like_count": 7,
                "quote_count": 0
            },
            "id": "1466734759153917954",
            "possibly_sensitive": false,
            "text": "On the latest #JamesBond A-Z Podcast, F is for #TomFord among other things.\n\nThe fashion label dressed Daniel Craig's 007 from #QuantumofSolace to #NoTimeToDie, and what a fine job they did too.\n\nListen &amp; learn more: https://t.co/xbjZyd5sCg https://t.co/gjUpghxOti",
            "author_id": "1334086431308857350",
            "created_at": "2021-12-03T11:43:11.000Z"
        },
        {
            "lang": "en",
            "public_metrics": {
                "retweet_count": 0,
                "reply_count": 0,
                "like_count": 1,
                "quote_count": 0
            },
            "id": "1466734458741026816",
            "possibly_sensitive": false,
            "text": "In the latest installment of the world\u2019s most beloved film franchise and agent James Bond, Daniel Craig suits up one last time as 007 in NO TIME TO DIE that will open in Philippine cinemas on December 15.     \n\nhttps://t.co/6SJ59Aa0dN",
            "author_id": "17644834",
            "created_at": "2021-12-03T11:42:00.000Z"
        },
        {
            "lang": "en",
            "public_metrics": {
                "retweet_count": 0,
                "reply_count": 0,
                "like_count": 4,
                "quote_count": 0
            },
            "id": "1466734375790383104",
            "possibly_sensitive": false,
            "text": "Shang-Chi or No Time To Die winning, I will be happy. \ud83d\ude0e https://t.co/dzJFZXq2X4",
            "author_id": "1290883207366234112",
            "created_at": "2021-12-03T11:41:40.000Z"
        },
        {
            "lang": "en",
            "public_metrics": {
                "retweet_count": 0,
                "reply_count": 0,
                "like_count": 0,
                "quote_count": 0
            },
            "id": "1466733317814902789",
            "possibly_sensitive": false,
            "text": "James Bond Comedy sketch film with @munyachawawa on his channel 4 show called \u2018Complaints welcome\u2019 #filming #actorslife  #acting #actor #fightscene #jamesbond  #comedy #specialeffects #notimetodie #channel4 https://t.co/yKIrR6Oq7v",
            "author_id": "38296029",
            "created_at": "2021-12-03T11:37:28.000Z"
        },
        {
            "lang": "en",
            "public_metrics": {
                "retweet_count": 0,
                "reply_count": 0,
                "like_count": 0,
                "quote_count": 0
            },
            "id": "1466733207521480715",
            "possibly_sensitive": false,
            "text": "Billie Eilish - No Time To Die https://t.co/Cqus9VIseU via @YouTube",
            "author_id": "1440080189300432899",
            "created_at": "2021-12-03T11:37:01.000Z"
        },
        {
            "lang": "en",
            "public_metrics": {
                "retweet_count": 0,
                "reply_count": 0,
                "like_count": 0,
                "quote_count": 0
            },
            "id": "1466733187971760130",
            "possibly_sensitive": false,
            "text": "No Time to Die was 10/10. Perfect send off for Daniel Craig \ud83d\udc4f\ud83c\udffe",
            "author_id": "244137927",
            "created_at": "2021-12-03T11:36:57.000Z"
        },
        {
            "lang": "en",
            "public_metrics": {
                "retweet_count": 0,
                "reply_count": 0,
                "like_count": 2,
                "quote_count": 0
            },
            "id": "1466732565474287618",
            "possibly_sensitive": false,
            "text": "THURSDAY'S TOP 5 FILMS FOR THE UK &amp; IRELAND:\n\n1 - #HouseOfGucci  \n2 - #Ghostbusters: Afterlife\n3 - #Encanto \n4 - #NoTimeToDie \n5 - #Dune",
            "author_id": "253294652",
            "created_at": "2021-12-03T11:34:28.000Z"
        },
        {
            "lang": "en",
            "public_metrics": {
                "retweet_count": 0,
                "reply_count": 0,
                "like_count": 0,
                "quote_count": 0
            },
            "id": "1466730900733972483",
            "possibly_sensitive": false,
            "text": "The latest The David W. Oakland Daily! https://t.co/7QD9O6WQQv Thanks to @rickygervais @GuardianBooks #notimetodie #undertheskin",
            "author_id": "3240209267",
            "created_at": "2021-12-03T11:27:51.000Z"
        },
        {
            "lang": "en",
            "public_metrics": {
                "retweet_count": 0,
                "reply_count": 0,
                "like_count": 0,
                "quote_count": 0
            },
            "id": "1466730700103684101",
            "possibly_sensitive": false,
            "text": "*** Many thanks to all our Supporting Artists who worked on #NoTimeToDie ***   - Why Is Nobody Is Talking About James Bond's $4000 'No Time to Die' Car? - -  https://t.co/gctZrZzwVu - #cars #car #motor #motoring #petrolheads https://t.co/obZ1B8x6mK",
            "author_id": "2180084605",
            "created_at": "2021-12-03T11:27:04.000Z"
        },
        {
            "lang": "en",
            "public_metrics": {
                "retweet_count": 0,
                "reply_count": 0,
                "like_count": 0,
                "quote_count": 0
            },
            "id": "1466730371404513284",
            "possibly_sensitive": false,
            "text": "#Catawiki James Bond 007: No Time To Die - Daniel Craig (007) - David Vijsma Glitch Art - Framed - Kunstwerk solid brass plate one off https://t.co/OuUXLXMsNf",
            "author_id": "43675707",
            "created_at": "2021-12-03T11:25:45.000Z"
        },
        {
            "lang": "en",
            "public_metrics": {
                "retweet_count": 0,
                "reply_count": 0,
                "like_count": 0,
                "quote_count": 0
            },
            "id": "1466728687366139904",
            "possibly_sensitive": false,
            "text": "'No Time To Die' Hits VOD Today https://t.co/3iqSHn1NBp https://t.co/TNm4rSB6OV",
            "author_id": "2150621544",
            "created_at": "2021-12-03T11:19:04.000Z"
        },
        {
            "lang": "en",
            "public_metrics": {
                "retweet_count": 1,
                "reply_count": 0,
                "like_count": 1,
                "quote_count": 0
            },
            "id": "1466727059217125384",
            "possibly_sensitive": false,
            "text": "Good morning @GoldsboroBooks . Is there a delay in delivery of the @TonyKent_Writes special edition of No Time To Die? I ordered on 4th Nov. Thanks. Andy",
            "author_id": "291603879",
            "geo": {
                "place_id": "7a6fb7508ad50ef3"
            },
            "created_at": "2021-12-03T11:12:36.000Z"
        },
        {
            "lang": "en",
            "public_metrics": {
                "retweet_count": 0,
                "reply_count": 0,
                "like_count": 0,
                "quote_count": 0
            },
            "id": "1466726753934712837",
            "possibly_sensitive": false,
            "text": "Still haven\u2019t emotionally recovered from No Time To die",
            "author_id": "1386955632851443712",
            "created_at": "2021-12-03T11:11:23.000Z"
        },
        {
            "lang": "en",
            "public_metrics": {
                "retweet_count": 0,
                "reply_count": 0,
                "like_count": 0,
                "quote_count": 0
            },
            "id": "1466726381832871937",
            "possibly_sensitive": false,
            "text": "The latest The Newsroom Daily! https://t.co/iwop3lhtSF Thanks to @mathewi #tomorrowspaperstoday #notimetodie",
            "author_id": "1933901666",
            "created_at": "2021-12-03T11:09:54.000Z"
        },
        {
            "lang": "en",
            "public_metrics": {
                "retweet_count": 0,
                "reply_count": 0,
                "like_count": 0,
                "quote_count": 0
            },
            "id": "1466725245826572293",
            "possibly_sensitive": false,
            "text": "No time to die https://t.co/1t8YHqI0Mv",
            "author_id": "947394835",
            "created_at": "2021-12-03T11:05:23.000Z"
        },
        {
            "lang": "en",
            "public_metrics": {
                "retweet_count": 0,
                "reply_count": 0,
                "like_count": 0,
                "quote_count": 0
            },
            "id": "1466725060891324421",
            "possibly_sensitive": false,
            "text": "No time to Die\ud83c\udfac 8/10",
            "author_id": "1174215234246066178",
            "created_at": "2021-12-03T11:04:39.000Z"
        },
        {
            "lang": "en",
            "public_metrics": {
                "retweet_count": 0,
                "reply_count": 0,
                "like_count": 4,
                "quote_count": 0
            },
            "id": "1466724020733235204",
            "possibly_sensitive": false,
            "text": "Not been to the cinema in a while? \nNever fear, we have this wonderful array next week.\n#HouseOfGucci, #PiratesFilm, #PetiteMaman, #GhostbustersAfterlife, #TheFrenchDispatch, #NoTimeToDie, #MotheringSunday, #Godzilla1954 and #TheMatrix 4K Restoration. \nhttps://t.co/O8Mq11t5Uc https://t.co/u1cyMCMRvb",
            "author_id": "30848722",
            "created_at": "2021-12-03T11:00:31.000Z"
        },
        {
            "lang": "en",
            "public_metrics": {
                "retweet_count": 0,
                "reply_count": 0,
                "like_count": 0,
                "quote_count": 0
            },
            "id": "1466723894535114752",
            "possibly_sensitive": false,
            "text": "#NoTimeToDie is everything you want from a #Bond movie. Will you be catching it this weekend?\n\nhttps://t.co/QFZB4xlJZP",
            "author_id": "1174198079278518272",
            "created_at": "2021-12-03T11:00:01.000Z"
        },
        {
            "lang": "en",
            "public_metrics": {
                "retweet_count": 0,
                "reply_count": 0,
                "like_count": 0,
                "quote_count": 0
            },
            "id": "1466723288894382084",
            "possibly_sensitive": false,
            "text": "No Time To D\u0130E..",
            "author_id": "313991214",
            "created_at": "2021-12-03T10:57:37.000Z"
        },
        {
            "lang": "en",
            "public_metrics": {
                "retweet_count": 0,
                "reply_count": 0,
                "like_count": 0,
                "quote_count": 0
            },
            "id": "1466722140615589890",
            "possibly_sensitive": false,
            "text": "James Bond No Time To Die Land Rover on show at British Motor Museum - https://t.co/RbA6NWzjzi https://t.co/5oLUK6uwkJ",
            "author_id": "378535737",
            "created_at": "2021-12-03T10:53:03.000Z"
        },
        {
            "lang": "en",
            "public_metrics": {
                "retweet_count": 0,
                "reply_count": 0,
                "like_count": 0,
                "quote_count": 0
            },
            "id": "1466721869441159173",
            "possibly_sensitive": false,
            "text": "\ud83c\udf0c\ud83d\udda4\nBillie Eilish - No Time To Die https://t.co/THn30J4Iuo via @YouTube",
            "author_id": "1179433748162662400",
            "created_at": "2021-12-03T10:51:58.000Z"
        },
        {
            "lang": "en",
            "public_metrics": {
                "retweet_count": 3,
                "reply_count": 1,
                "like_count": 26,
                "quote_count": 0
            },
            "id": "1466721118329393153",
            "possibly_sensitive": false,
            "text": "The happy have\nno urge to cry\n\nThe learned do not\nwonder why\n\nThe honest have \nno need to lie\n\nThe lovers have\nno time to die\n\n#RockAndVerse 125",
            "author_id": "1364338485482708992",
            "created_at": "2021-12-03T10:48:59.000Z"
        },
        {
            "lang": "en",
            "public_metrics": {
                "retweet_count": 0,
                "reply_count": 0,
                "like_count": 1,
                "quote_count": 0
            },
            "id": "1466717915575558147",
            "possibly_sensitive": false,
            "text": "Currently, lagi suka No Time To Die - Billie Eilish https://t.co/G4a8oZPP2z",
            "author_id": "1420994686819340291",
            "created_at": "2021-12-03T10:36:16.000Z"
        },
        {
            "lang": "en",
            "public_metrics": {
                "retweet_count": 1,
                "reply_count": 0,
                "like_count": 1,
                "quote_count": 0
            },
            "id": "1466717865546035201",
            "possibly_sensitive": false,
            "text": "KFTV Sustainability Talk\nTop experts working on #thecrown, #JurassicWorldDominion, #NoTimeToDie and \n@itvstudios projects discussed the hot topics of sustainable production on 1 December\n@ProdServNetwork @UniversalPics @netflix @EBU_HQ @Neptune_Enviro \nhttps://t.co/j80VMhenVJ",
            "author_id": "444778502",
            "created_at": "2021-12-03T10:36:04.000Z"
        },
        {
            "lang": "en",
            "public_metrics": {
                "retweet_count": 0,
                "reply_count": 0,
                "like_count": 0,
                "quote_count": 0
            },
            "id": "1466716860934668289",
            "possibly_sensitive": false,
            "text": "Billie Eilish - No Time To Die (Audio) https://t.co/wc8lSTimRI via @YouTube",
            "author_id": "740420737",
            "created_at": "2021-12-03T10:32:04.000Z"
        },
        {
            "lang": "en",
            "public_metrics": {
                "retweet_count": 0,
                "reply_count": 0,
                "like_count": 1,
                "quote_count": 0
            },
            "id": "1466716121692782593",
            "possibly_sensitive": false,
            "text": "The Unbreakable and no time to die soundtracks have some odd similarities",
            "author_id": "1264451531195265024",
            "created_at": "2021-12-03T10:29:08.000Z"
        },
        {
            "lang": "en",
            "public_metrics": {
                "retweet_count": 0,
                "reply_count": 1,
                "like_count": 9,
                "quote_count": 0
            },
            "id": "1466714849057001475",
            "possibly_sensitive": false,
            "text": "omfg just watched no time to die wtf",
            "author_id": "4676835374",
            "created_at": "2021-12-03T10:24:04.000Z"
        },
        {
            "lang": "en",
            "public_metrics": {
                "retweet_count": 0,
                "reply_count": 1,
                "like_count": 0,
                "quote_count": 0
            },
            "id": "1466710908239896582",
            "possibly_sensitive": false,
            "text": "Nobody wanted this. James Bond *without* James Bond = Woke Garbage, and this role-appropriating booner has gone far enough. \"Y'all focused on the uuhite man too long, and it's time to think bigger! OUR time to think bigger!\" The gall on this cock roach.\n\nhttps://t.co/J1X1t2Isvs",
            "author_id": "1215436068708728832",
            "created_at": "2021-12-03T10:08:25.000Z"
        },
        {
            "lang": "en",
            "public_metrics": {
                "retweet_count": 0,
                "reply_count": 0,
                "like_count": 1,
                "quote_count": 0
            },
            "id": "1466709766936350721",
            "possibly_sensitive": false,
            "text": "No time to die, tapos... #007",
            "author_id": "842572387421839360",
            "created_at": "2021-12-03T10:03:53.000Z"
        },
        {
            "lang": "en",
            "public_metrics": {
                "retweet_count": 2,
                "reply_count": 0,
                "like_count": 5,
                "quote_count": 0
            },
            "id": "1466709476132720645",
            "possibly_sensitive": false,
            "text": "Who\u2019s ready for today\u2019s episode of Common Ground?\n\nTune in to @tu_xtra this afternoon to watch this week\u2019s guests discuss the newest Bond film - No Time To Die\ud83d\udd75\ufe0f\u200d\u2642\ufe0f \n\n@TeessideUni #broadcast #webseries #jamesbond\n#notimetodie https://t.co/bzGQX23Mfw",
            "author_id": "1458477706069295113",
            "created_at": "2021-12-03T10:02:43.000Z"
        },
        {
            "lang": "en",
            "public_metrics": {
                "retweet_count": 0,
                "reply_count": 1,
                "like_count": 10,
                "quote_count": 0
            },
            "id": "1466706691043610626",
            "possibly_sensitive": false,
            "text": "Now you\u2019ll never see me cry \nThere\u2019s just no time to die",
            "author_id": "187391077",
            "created_at": "2021-12-03T09:51:39.000Z"
        },
        {
            "lang": "en",
            "public_metrics": {
                "retweet_count": 0,
                "reply_count": 1,
                "like_count": 1,
                "quote_count": 0
            },
            "id": "1466706606893191169",
            "possibly_sensitive": false,
            "text": "army of thieves was better than no time to die and i mean that w my chest",
            "author_id": "1141446977227501573",
            "created_at": "2021-12-03T09:51:19.000Z"
        },
        {
            "lang": "en",
            "public_metrics": {
                "retweet_count": 0,
                "reply_count": 0,
                "like_count": 2,
                "quote_count": 0
            },
            "id": "1466705850991464448",
            "possibly_sensitive": false,
            "text": "i\u2019ll never forgive sony for having james bond say \u2018we have all the time in the world\u2019 and then have him DIE at the end of no time to die. RUDE, i\u2019m never gonna recover from this",
            "author_id": "893662967429857285",
            "created_at": "2021-12-03T09:48:19.000Z"
        },
        {
            "lang": "en",
            "public_metrics": {
                "retweet_count": 0,
                "reply_count": 0,
                "like_count": 5,
                "quote_count": 0
            },
            "id": "1466704259538247681",
            "possibly_sensitive": false,
            "text": "Watched #NoTimeToDie today in the cinema \ud83c\udfa5 omg the ending \ud83d\ude2d\ud83d\ude2dwas so sad I crying so much coming out of the movies \ud83c\udfac",
            "author_id": "4807665740",
            "created_at": "2021-12-03T09:42:00.000Z"
        },
        {
            "lang": "en",
            "public_metrics": {
                "retweet_count": 0,
                "reply_count": 0,
                "like_count": 1,
                "quote_count": 0
            },
            "id": "1466703535609991169",
            "possibly_sensitive": false,
            "text": "Casino Royale-10\n\nQuantum Of Solace-12\n\nSkyfall-16\n\nSpectre-19\n\nNo Time To Die-25 https://t.co/jleZ9Eh6el",
            "author_id": "1448024318",
            "created_at": "2021-12-03T09:39:07.000Z"
        },
        {
            "lang": "en",
            "public_metrics": {
                "retweet_count": 0,
                "reply_count": 0,
                "like_count": 0,
                "quote_count": 0
            },
            "id": "1466700498875072515",
            "possibly_sensitive": false,
            "text": "*** Many thanks to all our Supporting Artists who worked on #NoTimeToDie ***   - Ryan Reynolds Talks Being Open To Playing James Bond, And It\u2019s Actually Not The First Time He\u2019s Been Suggested - https://t.co/9ZeUExam0d https://t.co/EYzse1jj7H",
            "author_id": "2180084605",
            "created_at": "2021-12-03T09:27:03.000Z"
        },
        {
            "lang": "en",
            "public_metrics": {
                "retweet_count": 0,
                "reply_count": 1,
                "like_count": 0,
                "quote_count": 0
            },
            "id": "1466700019159863296",
            "possibly_sensitive": false,
            "text": "First time tengok movie james bond. Ana de armas is bae \ud83d\ude0d #NoTimeToDie",
            "author_id": "854332993",
            "created_at": "2021-12-03T09:25:09.000Z"
        },
        {
            "lang": "en",
            "public_metrics": {
                "retweet_count": 0,
                "reply_count": 0,
                "like_count": 0,
                "quote_count": 0
            },
            "id": "1466699260628389889",
            "possibly_sensitive": false,
            "text": "Warning: Contains spoilers\nSee my review of #NoTimeToDie on @letterboxd - https://t.co/UIIINpJ3tN",
            "author_id": "1029964129488883712",
            "created_at": "2021-12-03T09:22:08.000Z"
        },
        {
            "lang": "en",
            "public_metrics": {
                "retweet_count": 0,
                "reply_count": 1,
                "like_count": 0,
                "quote_count": 0
            },
            "id": "1466699002074832903",
            "possibly_sensitive": false,
            "text": "Watching it again wide awake at 4 am it's probably for the best that I started intermittently dozing off around minute 75 of No Time to Die in the theater.",
            "author_id": "747276951287566337",
            "created_at": "2021-12-03T09:21:06.000Z"
        },
        {
            "lang": "en",
            "public_metrics": {
                "retweet_count": 0,
                "reply_count": 0,
                "like_count": 1,
                "quote_count": 0
            },
            "id": "1466697509414359041",
            "possibly_sensitive": false,
            "text": "6 Casino Royale \n21 No Time To Die https://t.co/oq5cQgtn0h",
            "author_id": "842227919892160512",
            "created_at": "2021-12-03T09:15:10.000Z"
        },
        {
            "lang": "en",
            "public_metrics": {
                "retweet_count": 0,
                "reply_count": 0,
                "like_count": 0,
                "quote_count": 0
            },
            "id": "1466690579874471938",
            "possibly_sensitive": false,
            "text": "Check out this No Time To Die piano arrangement I wrote. https://t.co/zDFux8M6To https://t.co/9CYROK4Gyg",
            "author_id": "283604227",
            "created_at": "2021-12-03T08:47:38.000Z"
        },
        {
            "lang": "en",
            "public_metrics": {
                "retweet_count": 0,
                "reply_count": 0,
                "like_count": 0,
                "quote_count": 0
            },
            "id": "1466690250353250306",
            "possibly_sensitive": false,
            "text": "ZSJL\nDune\nNo time to die",
            "author_id": "825262076",
            "created_at": "2021-12-03T08:46:20.000Z"
        },
        {
            "lang": "en",
            "public_metrics": {
                "retweet_count": 0,
                "reply_count": 0,
                "like_count": 0,
                "quote_count": 0
            },
            "id": "1466689620121251840",
            "possibly_sensitive": false,
            "text": "\u2018No Time To Die\u2019 was a cinematic spectacle. Rami Malek was commanding, as usual. Go see it.\n\ud83c\udfa5 \ud83c\udf7f #NoTimeToDie",
            "author_id": "50701187",
            "created_at": "2021-12-03T08:43:49.000Z"
        },
        {
            "lang": "en",
            "public_metrics": {
                "retweet_count": 0,
                "reply_count": 0,
                "like_count": 2,
                "quote_count": 0
            },
            "id": "1466687593421045762",
            "possibly_sensitive": false,
            "text": "I thought \u2018No Time To Die\u2019 was spectacular on many levels. However, no need to recast Bond. We have our new 007 and she is played by the incredible Lashana Lynch. I want to see more of her character and will happily pay to see how the current story continues with her.",
            "author_id": "20881812",
            "created_at": "2021-12-03T08:35:46.000Z"
        },
        {
            "lang": "en",
            "public_metrics": {
                "retweet_count": 0,
                "reply_count": 1,
                "like_count": 2,
                "quote_count": 0
            },
            "id": "1466687428207398916",
            "possibly_sensitive": false,
            "text": "No time to die 100/10 \ud83d\ude2d\ud83d\ude2d\ud83d\ude2d\ud83d\ude2d",
            "author_id": "603544707",
            "created_at": "2021-12-03T08:35:07.000Z"
        },
        {
            "lang": "en",
            "public_metrics": {
                "retweet_count": 0,
                "reply_count": 0,
                "like_count": 0,
                "quote_count": 0
            },
            "id": "1466687019493388288",
            "possibly_sensitive": false,
            "text": "I just rated No Time to Die (2021) 6/7 on #imdb https://t.co/9IfnVIyOnZ",
            "author_id": "12858552",
            "created_at": "2021-12-03T08:33:29.000Z"
        },
        {
            "lang": "en",
            "public_metrics": {
                "retweet_count": 0,
                "reply_count": 0,
                "like_count": 1,
                "quote_count": 0
            },
            "id": "1466686897703596035",
            "possibly_sensitive": false,
            "text": "The function of man is to live,not to exist.I shall not use my days to prolong,i should use my time,for there is NO TIME TO DIE",
            "author_id": "1396405930678525960",
            "created_at": "2021-12-03T08:33:00.000Z"
        },
        {
            "lang": "en",
            "public_metrics": {
                "retweet_count": 0,
                "reply_count": 0,
                "like_count": 3,
                "quote_count": 0
            },
            "id": "1466686140296093701",
            "possibly_sensitive": false,
            "text": "I\u2019m currently binging all the Daniel Craig era Bond movies prior to watching #NoTimeToDie. This has nothing much to do with this 1978 Series III #LandRover 88 but the location has. Just over the hill there is (or rather was) Skyfall House (and this is deepest Surrey not Scotland) https://t.co/V9PqzLSOEq",
            "author_id": "181133978",
            "created_at": "2021-12-03T08:30:00.000Z"
        },
        {
            "lang": "en",
            "public_metrics": {
                "retweet_count": 0,
                "reply_count": 0,
                "like_count": 0,
                "quote_count": 0
            },
            "id": "1466685284758835200",
            "possibly_sensitive": false,
            "text": "That club in no time to die looked a vibe",
            "author_id": "1499122471",
            "created_at": "2021-12-03T08:26:36.000Z"
        },
        {
            "lang": "en",
            "public_metrics": {
                "retweet_count": 0,
                "reply_count": 0,
                "like_count": 0,
                "quote_count": 0
            },
            "id": "1466680899601412099",
            "possibly_sensitive": false,
            "text": "23 - Casino Royale (November 2006)\n37 - No Time to Die (September 2021)\n\n\ud83d\ude31 https://t.co/2NQcYxRO4w",
            "author_id": "466367018",
            "created_at": "2021-12-03T08:09:10.000Z"
        },
        {
            "lang": "en",
            "public_metrics": {
                "retweet_count": 0,
                "reply_count": 0,
                "like_count": 0,
                "quote_count": 0
            },
            "id": "1466680782542409732",
            "possibly_sensitive": false,
            "text": "...so when did the #JamesBond series turn into the #ToAllTheGirlsILovedBefore series? \n\n#NoTimeToDie \n\nPS- @mgmstudios if you're not talking to Richard Madden yet, you shoul be. https://t.co/6vb2ni13EX",
            "author_id": "499025273",
            "created_at": "2021-12-03T08:08:42.000Z"
        },
        {
            "lang": "en",
            "public_metrics": {
                "retweet_count": 0,
                "reply_count": 0,
                "like_count": 0,
                "quote_count": 0
            },
            "id": "1466680552094720009",
            "possibly_sensitive": false,
            "text": "No time to Die.\nShang chi.\n#TheMatrix4  for sure https://t.co/9XTPWmmEiV",
            "author_id": "2186741024",
            "created_at": "2021-12-03T08:07:47.000Z"
        },
        {
            "lang": "en",
            "public_metrics": {
                "retweet_count": 0,
                "reply_count": 0,
                "like_count": 0,
                "quote_count": 0
            },
            "id": "1466680110677905409",
            "possibly_sensitive": false,
            "text": "Getting a taste of what the songs will be like..\nBillie Eilish - No Time to Die - Playano Overlay (Piano Cover)\nhttps://t.co/1UpWvOk90E\n#EdTech #Arttech #Metaverse #Playano #PianoHero #PianoChampion #PianoMaster #PianoSavant #ELearning #AR #Augmentedreality #Piano https://t.co/pgV3dAK9rZ",
            "author_id": "1414859780418457602",
            "created_at": "2021-12-03T08:06:02.000Z"
        },
        {
            "lang": "en",
            "public_metrics": {
                "retweet_count": 0,
                "reply_count": 1,
                "like_count": 0,
                "quote_count": 0
            },
            "id": "1466679752136310787",
            "possibly_sensitive": false,
            "text": "No time to die was a good movie",
            "author_id": "1175507466769129472",
            "created_at": "2021-12-03T08:04:37.000Z"
        },
        {
            "lang": "en",
            "public_metrics": {
                "retweet_count": 0,
                "reply_count": 0,
                "like_count": 0,
                "quote_count": 0
            },
            "id": "1466678958628519938",
            "possibly_sensitive": false,
            "text": "fast 9 - NO Time to Die Advance Booking Open..\n\nBook your tickets now...\n\n#cinepax\n#blackpink #bts #kpop #twice #exo #jennie #lisa #tickets #music #concert #ticket #livemusic #live #show #tour #events #travel #entertainment #party #festival #theatre #fun #event #comedy #danc\u2026 https://t.co/hcme8VdsTr",
            "author_id": "1484245333",
            "created_at": "2021-12-03T08:01:27.000Z"
        },
        {
            "lang": "en",
            "public_metrics": {
                "retweet_count": 0,
                "reply_count": 0,
                "like_count": 0,
                "quote_count": 0
            },
            "id": "1466678727291518979",
            "possibly_sensitive": false,
            "text": "WTF Spoil Alert: Daniel Craig's NO TIME TO DIE was selfish as fuck. If he didn't want to play @007 anymore, fine, but why kill Bond and Felix?\nEvery Bond film ends with \"James Bond Will Return\" but not this time.\nI suppose the next rehash will be YOU ONLY LIVE TWICE?.... \ud83d\udc4e\ud83c\udfff https://t.co/YXYRny5DRQ",
            "author_id": "91533568",
            "created_at": "2021-12-03T08:00:32.000Z"
        },
        {
            "lang": "en",
            "public_metrics": {
                "retweet_count": 0,
                "reply_count": 0,
                "like_count": 0,
                "quote_count": 0
            },
            "id": "1466676384114171904",
            "possibly_sensitive": false,
            "text": "no time to die",
            "author_id": "1376214164742545408",
            "created_at": "2021-12-03T07:51:14.000Z"
        },
        {
            "lang": "en",
            "public_metrics": {
                "retweet_count": 0,
                "reply_count": 0,
                "like_count": 0,
                "quote_count": 0
            },
            "id": "1466675175450202114",
            "possibly_sensitive": false,
            "text": "This is my 4th if not 5th day ke ntse ke lebile No time to die\ud83d\ude29\ud83e\udd26\ud83c\udffd\u200d\u2640\ufe0fe gana go hela",
            "author_id": "2765311173",
            "created_at": "2021-12-03T07:46:25.000Z"
        },
        {
            "lang": "en",
            "public_metrics": {
                "retweet_count": 0,
                "reply_count": 0,
                "like_count": 0,
                "quote_count": 0
            },
            "id": "1466675058068242432",
            "possibly_sensitive": false,
            "text": "Zack Snyder's Justice League\nDune\nNo Time To Die https://t.co/Kj1B3V4ABM",
            "author_id": "17749741",
            "created_at": "2021-12-03T07:45:58.000Z"
        },
        {
            "lang": "en",
            "public_metrics": {
                "retweet_count": 0,
                "reply_count": 0,
                "like_count": 1,
                "quote_count": 0
            },
            "id": "1466674805487329280",
            "possibly_sensitive": false,
            "text": "28- Casino Royale (November 2006)\n43- No Time To Die (September 2021) https://t.co/FUhVxLrCO3",
            "author_id": "454063640",
            "created_at": "2021-12-03T07:44:57.000Z"
        },
        {
            "lang": "en",
            "public_metrics": {
                "retweet_count": 1,
                "reply_count": 0,
                "like_count": 2,
                "quote_count": 0
            },
            "id": "1466674297838182409",
            "possibly_sensitive": false,
            "text": "No Time To Die Review https://t.co/9JmEA3Ykco",
            "author_id": "1373549737039818752",
            "created_at": "2021-12-03T07:42:56.000Z"
        },
        {
            "lang": "en",
            "public_metrics": {
                "retweet_count": 0,
                "reply_count": 0,
                "like_count": 0,
                "quote_count": 0
            },
            "id": "1466674285087494147",
            "possibly_sensitive": false,
            "text": "Me after reading #notimetodie is out on #4k before #Christmas #JamesBond https://t.co/9K2tUCTQDZ https://t.co/k0bdPab4Zb",
            "author_id": "1393111771",
            "created_at": "2021-12-03T07:42:53.000Z"
        },
        {
            "lang": "en",
            "public_metrics": {
                "retweet_count": 0,
                "reply_count": 0,
                "like_count": 2,
                "quote_count": 0
            },
            "id": "1466672897301544961",
            "possibly_sensitive": false,
            "text": "Rami Malek: 'You will be shocked by No Time To Die' | British GQ https://t.co/v8YkyVlBWC",
            "author_id": "819561961666985984",
            "created_at": "2021-12-03T07:37:22.000Z"
        },
        {
            "lang": "en",
            "public_metrics": {
                "retweet_count": 0,
                "reply_count": 0,
                "like_count": 0,
                "quote_count": 0
            },
            "id": "1466672521332371456",
            "possibly_sensitive": false,
            "text": "February 14th 2022 - April 3rd drink to this, see if you feel me,\n\nBillie Eilish - No Time To Die\" on YouTube https://t.co/FDpeHvj8bi https://t.co/iWK1p55bxE",
            "author_id": "1459337246583267330",
            "created_at": "2021-12-03T07:35:53.000Z"
        },
        {
            "lang": "en",
            "public_metrics": {
                "retweet_count": 0,
                "reply_count": 0,
                "like_count": 0,
                "quote_count": 0
            },
            "id": "1466671662468849668",
            "possibly_sensitive": false,
            "text": "I believe God but but I get confused sometimes I ain\u2019t gon\u2019 lie suicide has been on my mind but I ain\u2019t got no time to die like Billie Eilish",
            "author_id": "3181169946",
            "created_at": "2021-12-03T07:32:28.000Z"
        },
        {
            "lang": "en",
            "public_metrics": {
                "retweet_count": 3,
                "reply_count": 0,
                "like_count": 10,
                "quote_count": 1
            },
            "id": "1466671216219934720",
            "possibly_sensitive": false,
            "text": "Call me 007 from now on coz I too am always under cover. \ud83d\ude0e\n\n#JamesBond #NoTimeToDie #OnlyTimeToLie",
            "author_id": "1450680605193080832",
            "created_at": "2021-12-03T07:30:42.000Z"
        },
        {
            "lang": "en",
            "public_metrics": {
                "retweet_count": 0,
                "reply_count": 1,
                "like_count": 6,
                "quote_count": 1
            },
            "id": "1466671064948355075",
            "possibly_sensitive": false,
            "text": "This week @StiofanDonnelly is joined by Tess Farrell to review White Lotus, Only Murders in the Building, Succession S3, and No Time To Die in a monster Pop Culture wrap up episode (Warning: Spoilers!!!!!!!).  \n\nCheck it out Socially Democratic - https://t.co/CFFlruzRGm https://t.co/M66EJtTIat",
            "author_id": "1100937913351593984",
            "created_at": "2021-12-03T07:30:05.000Z"
        },
        {
            "lang": "en",
            "public_metrics": {
                "retweet_count": 0,
                "reply_count": 4,
                "like_count": 23,
                "quote_count": 1
            },
            "id": "1466670441066545154",
            "possibly_sensitive": false,
            "text": "21 for Casino Royale\n36 for No Time to Die\n\nSo I'll be 37 soon EON....\n\nI mean I'll still be 5ft 7 but I'll be a decent age for the role! \ud83d\ude1c\n\n#JamesBond #DanielCraig #NoTimeToDie #CasinoRoyale @007 https://t.co/YGQJqiJeP4",
            "author_id": "1089971244391456768",
            "created_at": "2021-12-03T07:27:37.000Z"
        },
        {
            "lang": "en",
            "public_metrics": {
                "retweet_count": 0,
                "reply_count": 1,
                "like_count": 2,
                "quote_count": 0
            },
            "id": "1466670296069513221",
            "possibly_sensitive": false,
            "text": "Quote tweet with how old you were during Daniel Craig\u2019s Bond films (release date). \n\n24 - Casino Royale (November 2006)\n39 - No Time to Die (September 2021) https://t.co/t0mJxqXnki",
            "author_id": "1218961696053776384",
            "created_at": "2021-12-03T07:27:02.000Z"
        },
        {
            "lang": "en",
            "public_metrics": {
                "retweet_count": 0,
                "reply_count": 0,
                "like_count": 0,
                "quote_count": 0
            },
            "id": "1466669852148613123",
            "possibly_sensitive": false,
            "text": "The beating down for #NASDAQ #index time is here. #NoTimeToDie but Time for Sell off is here big time.\n\n#DowJones already had its glass of selloff filled up. Slow down on it.\n\n#SP500 just the neutral ground for spectators to watch the #marketplace rumble.\n\n#cephaspobhlsp #trade",
            "author_id": "1252654943745556480",
            "created_at": "2021-12-03T07:25:16.000Z"
        },
        {
            "lang": "en",
            "public_metrics": {
                "retweet_count": 0,
                "reply_count": 0,
                "like_count": 0,
                "quote_count": 0
            },
            "id": "1466669588339437575",
            "possibly_sensitive": false,
            "text": "Kate Middleton in a Gold Dress Attends No Time to Die World Premiere at the Royal Albert Hall in London 09/28/2021 https://t.co/O4N2hTLTiY",
            "author_id": "1299310854232514560",
            "created_at": "2021-12-03T07:24:13.000Z"
        },
        {
            "lang": "en",
            "public_metrics": {
                "retweet_count": 0,
                "reply_count": 4,
                "like_count": 12,
                "quote_count": 4
            },
            "id": "1466669191013052420",
            "possibly_sensitive": false,
            "text": "Quote tweet with how old you were during Daniel Craig\u2019s Bond films (release date). \n\n16 - Casino Royale (November 2006)\n30 - No Time to Die (September 2021)\n\nBond for half my life. I am old. https://t.co/XrkcLcUEKL",
            "author_id": "60407454",
            "geo": {
                "place_id": "54f32ee3651e5dd7"
            },
            "created_at": "2021-12-03T07:22:39.000Z"
        },
        {
            "lang": "en",
            "public_metrics": {
                "retweet_count": 0,
                "reply_count": 0,
                "like_count": 0,
                "quote_count": 0
            },
            "id": "1466667948232392704",
            "possibly_sensitive": false,
            "text": "No time to die https://t.co/2Au1UYVb9o",
            "author_id": "152672768",
            "created_at": "2021-12-03T07:17:42.000Z"
        },
        {
            "lang": "en",
            "public_metrics": {
                "retweet_count": 0,
                "reply_count": 0,
                "like_count": 0,
                "quote_count": 0
            },
            "id": "1466667531347836928",
            "possibly_sensitive": false,
            "text": "#NowPlaying Billie Eilish - No Time To Die https://t.co/UrMnYKkUTk",
            "author_id": "3608373454",
            "created_at": "2021-12-03T07:16:03.000Z"
        },
        {
            "lang": "en",
            "public_metrics": {
                "retweet_count": 0,
                "reply_count": 0,
                "like_count": 0,
                "quote_count": 0
            },
            "id": "1466667252367851520",
            "possibly_sensitive": false,
            "text": "spoiler for no time to die:\n-\n-\n-\n-\n-\n-\n-\n-\n-\n-\n-\nthe first bond movie i watch and he literally dies wtf \ud83d\ude2d\ud83d\ude2d",
            "author_id": "1361946261612490752",
            "created_at": "2021-12-03T07:14:56.000Z"
        },
        {
            "lang": "en",
            "public_metrics": {
                "retweet_count": 0,
                "reply_count": 0,
                "like_count": 0,
                "quote_count": 0
            },
            "id": "1466666916697702401",
            "possibly_sensitive": false,
            "text": "34 Casino Royale \n49 No Time To Die \n\ud83d\ude33 https://t.co/rPuvVb1MQW",
            "author_id": "705451094084816896",
            "created_at": "2021-12-03T07:13:36.000Z"
        },
        {
            "lang": "en",
            "public_metrics": {
                "retweet_count": 0,
                "reply_count": 1,
                "like_count": 1,
                "quote_count": 0
            },
            "id": "1466666794039402497",
            "possibly_sensitive": false,
            "text": "1. Last Night Soho\n2. Dune\n3. No Time to Die https://t.co/5M2LhdI60M",
            "author_id": "1360413053133627392",
            "created_at": "2021-12-03T07:13:07.000Z"
        }
    ],
    "meta": {
        "newest_id": "1466750729406795776",
        "oldest_id": "1466666794039402497",
        "result_count": 100,
        "next_token": "b26v89c19zqg8o3fpdy83gfd2j0sykdilau98wgonad19"
    }
}