{
    "data": [
        {
            "id": "1467138693550989314",
            "public_metrics": {
                "retweet_count": 0,
                "reply_count": 0,
                "like_count": 3,
                "quote_count": 0
            },
            "created_at": "2021-12-04T14:28:17.000Z",
            "text": "I wish Rebecca Ferguson could have played ALL the characters in Dune...",
            "possibly_sensitive": false,
            "author_id": "2426112722",
            "lang": "en"
        },
        {
            "id": "1467138392441831426",
            "public_metrics": {
                "retweet_count": 0,
                "reply_count": 1,
                "like_count": 0,
                "quote_count": 0
            },
            "created_at": "2021-12-04T14:27:05.000Z",
            "text": "no thoughts just, timothee chalamet in dune as paul atreides",
            "possibly_sensitive": false,
            "author_id": "1375775939892678660",
            "lang": "en"
        },
        {
            "id": "1467138309856108545",
            "public_metrics": {
                "retweet_count": 0,
                "reply_count": 0,
                "like_count": 1,
                "quote_count": 0
            },
            "created_at": "2021-12-04T14:26:45.000Z",
            "text": "yes im considering going to see dune again, no one look at me",
            "possibly_sensitive": false,
            "author_id": "1371574067829030916",
            "lang": "en"
        },
        {
            "id": "1467138288158924802",
            "public_metrics": {
                "retweet_count": 0,
                "reply_count": 0,
                "like_count": 1,
                "quote_count": 0
            },
            "created_at": "2021-12-04T14:26:40.000Z",
            "text": "Going to Mars is like the novel Dune.\n\nOnly there\u2019s no spice and nobody is making us do it.\n\nAlso we completely optionally destroyed the paradise planet we were living on before we left",
            "possibly_sensitive": false,
            "author_id": "305796532",
            "lang": "en"
        },
        {
            "id": "1467138286292455424",
            "public_metrics": {
                "retweet_count": 0,
                "reply_count": 0,
                "like_count": 2,
                "quote_count": 0
            },
            "created_at": "2021-12-04T14:26:40.000Z",
            "text": "#TimotheeChalamet didn\u2019t disappoint \ud83d\ude01. I didn\u2019t have high expectations from the new movie #Dune but it was surprisingly interesting and more explicit than the previous one. Good visuals and actors. Waiting for the part 2. #Dune2021 #whattowatch",
            "possibly_sensitive": false,
            "author_id": "2535719190",
            "lang": "en"
        },
        {
            "id": "1467138193128574983",
            "public_metrics": {
                "retweet_count": 0,
                "reply_count": 3,
                "like_count": 21,
                "quote_count": 0
            },
            "created_at": "2021-12-04T14:26:18.000Z",
            "text": "It turns out Jeff and I can ramble exceptionally well. Thankfully, we didn\u2019t end up talking about Dune, the podcast would have been 7 hours. https://t.co/6dZ1F5CgkD",
            "possibly_sensitive": false,
            "author_id": "266840843",
            "lang": "en"
        },
        {
            "id": "1467138107036213249",
            "public_metrics": {
                "retweet_count": 0,
                "reply_count": 0,
                "like_count": 4,
                "quote_count": 0
            },
            "created_at": "2021-12-04T14:25:57.000Z",
            "text": "Local Perth queer contributes to 40% of Dune box office sales.",
            "possibly_sensitive": false,
            "author_id": "296745454",
            "lang": "en"
        },
        {
            "id": "1467137636875780096",
            "public_metrics": {
                "retweet_count": 0,
                "reply_count": 0,
                "like_count": 1,
                "quote_count": 0
            },
            "created_at": "2021-12-04T14:24:05.000Z",
            "text": "Someone in this cafe is reading dune. Just casually reading it in a loud ass cafe. Like what",
            "possibly_sensitive": false,
            "author_id": "1421313697935499264",
            "lang": "en"
        },
        {
            "id": "1467137507313827842",
            "public_metrics": {
                "retweet_count": 0,
                "reply_count": 0,
                "like_count": 0,
                "quote_count": 0
            },
            "created_at": "2021-12-04T14:23:34.000Z",
            "text": "strippers from dune hit different https://t.co/tcoR0qKwvl",
            "possibly_sensitive": false,
            "author_id": "230863656",
            "lang": "en"
        },
        {
            "id": "1467137320642088963",
            "public_metrics": {
                "retweet_count": 0,
                "reply_count": 0,
                "like_count": 2,
                "quote_count": 0
            },
            "created_at": "2021-12-04T14:22:49.000Z",
            "text": "I've never done two movies back to back at a theater during a pandemic. Today is that day, my present to myself. Dune and Eternals, here I come. I'll celebrate my name day with you. \ud83e\udd73",
            "possibly_sensitive": false,
            "author_id": "1405519142942384130",
            "lang": "en"
        },
        {
            "id": "1467137277075857413",
            "public_metrics": {
                "retweet_count": 3,
                "reply_count": 4,
                "like_count": 57,
                "quote_count": 0
            },
            "created_at": "2021-12-04T14:22:39.000Z",
            "text": "Thoughts while reading Dune: Duncan Idaho (or Donnchadh \"Idaho\") sounds like a nickname someone in Uist might have for no real reason.",
            "possibly_sensitive": false,
            "author_id": "891967618248302592",
            "lang": "en"
        },
        {
            "id": "1467136315921629186",
            "public_metrics": {
                "retweet_count": 0,
                "reply_count": 0,
                "like_count": 0,
                "quote_count": 0
            },
            "created_at": "2021-12-04T14:18:50.000Z",
            "text": "WHY ARE PEOPLE COMPLAINING ABOUT DUNE I DONT GET IT",
            "possibly_sensitive": false,
            "author_id": "1401056964893843456",
            "lang": "en"
        },
        {
            "id": "1467136283508023299",
            "public_metrics": {
                "retweet_count": 0,
                "reply_count": 0,
                "like_count": 0,
                "quote_count": 0
            },
            "created_at": "2021-12-04T14:18:42.000Z",
            "text": "So, the movie Dune was odd....",
            "possibly_sensitive": false,
            "author_id": "1237603652560236551",
            "lang": "en"
        },
        {
            "id": "1467136188704251907",
            "public_metrics": {
                "retweet_count": 69,
                "reply_count": 2,
                "like_count": 458,
                "quote_count": 4
            },
            "created_at": "2021-12-04T14:18:20.000Z",
            "text": "pauline chalamet could do dune but timothee chalamet couldn\u2019t do sex lives of college girls",
            "possibly_sensitive": false,
            "author_id": "563229109",
            "lang": "en"
        },
        {
            "id": "1467135488041664514",
            "public_metrics": {
                "retweet_count": 0,
                "reply_count": 0,
                "like_count": 2,
                "quote_count": 0
            },
            "created_at": "2021-12-04T14:15:33.000Z",
            "text": "Got a couple of games in yesterday; Res Arcana by Tom Lehmann @SandCastleGame1 a fun strategy game w/fast, easy set up. Then Dune Imperium by @Legendary. Love the complexity &amp; strategy involved. I highly recommend both, they live up to the hype! #boardgames #tabletopgaming #bgg https://t.co/m8Afi6qFVJ",
            "possibly_sensitive": false,
            "author_id": "1355942965806592003",
            "lang": "en"
        },
        {
            "id": "1467134962218541059",
            "public_metrics": {
                "retweet_count": 0,
                "reply_count": 2,
                "like_count": 3,
                "quote_count": 0
            },
            "created_at": "2021-12-04T14:13:27.000Z",
            "text": "Right... Next up in town... DUNE!!! https://t.co/ODvWIrbry1",
            "possibly_sensitive": false,
            "author_id": "5926092",
            "lang": "en"
        },
        {
            "id": "1467134881289281536",
            "public_metrics": {
                "retweet_count": 0,
                "reply_count": 1,
                "like_count": 7,
                "quote_count": 0
            },
            "created_at": "2021-12-04T14:13:08.000Z",
            "text": "I saw Dune today and thought it was a brilliant film and a great adaptation of the novel. One thing I will say that if it is possible do go and see it in the cinema. It\u2019s a film that really benefits from the big screen and big sound.",
            "possibly_sensitive": false,
            "author_id": "1214398045724364800",
            "lang": "en"
        },
        {
            "id": "1467134776784171014",
            "public_metrics": {
                "retweet_count": 5,
                "reply_count": 0,
                "like_count": 30,
                "quote_count": 0
            },
            "created_at": "2021-12-04T14:12:43.000Z",
            "text": "Hey ladies, seen Dune yet? Would love to treat you to a matinee and a couple tubs of popcorn. I love powerful women btw https://t.co/f4OWcPALc5",
            "possibly_sensitive": false,
            "author_id": "1330656464600526848",
            "lang": "en"
        },
        {
            "id": "1467134648832692225",
            "public_metrics": {
                "retweet_count": 57,
                "reply_count": 1,
                "like_count": 377,
                "quote_count": 5
            },
            "created_at": "2021-12-04T14:12:12.000Z",
            "text": "The Atreides 'thopter is looking a little crowded with @GreigfraserD and Denis Villeneuve overseeing the Spice Mining inspection filming in #DuneMovie https://t.co/jcVHviofs3",
            "possibly_sensitive": false,
            "author_id": "36073989",
            "lang": "en"
        },
        {
            "id": "1467134448911228934",
            "public_metrics": {
                "retweet_count": 0,
                "reply_count": 0,
                "like_count": 0,
                "quote_count": 0
            },
            "created_at": "2021-12-04T14:11:25.000Z",
            "text": "The 16th years old @daviddamiano99 should watch Dune\u2728",
            "possibly_sensitive": false,
            "author_id": "1874632458",
            "lang": "en"
        },
        {
            "id": "1467134424294862849",
            "public_metrics": {
                "retweet_count": 1,
                "reply_count": 0,
                "like_count": 2,
                "quote_count": 0
            },
            "created_at": "2021-12-04T14:11:19.000Z",
            "text": "\"DOONT\" \u2014 A Bad Lip Reading of Dune https://t.co/iN9TQ8AxMW",
            "possibly_sensitive": false,
            "author_id": "35063180",
            "lang": "en"
        },
        {
            "id": "1467134380124651530",
            "public_metrics": {
                "retweet_count": 0,
                "reply_count": 0,
                "like_count": 0,
                "quote_count": 0
            },
            "created_at": "2021-12-04T14:11:08.000Z",
            "text": "Dune - https://t.co/mQdxP3ZSjJ https://t.co/bJbXJINJwZ",
            "possibly_sensitive": false,
            "author_id": "3186904726",
            "lang": "en"
        },
        {
            "id": "1467133633655885824",
            "public_metrics": {
                "retweet_count": 0,
                "reply_count": 1,
                "like_count": 4,
                "quote_count": 0
            },
            "created_at": "2021-12-04T14:08:10.000Z",
            "text": "Is it my age or what? All the famous new movies have turned out to be utterly boring and disappointing for me. Just two examples:\nDune\nNo time to die\n\nWaste of time really. Forced me to watch old movies again: Godfather, Once upon a time in America, Scarface, Shawshank Redemption",
            "possibly_sensitive": false,
            "author_id": "57280404",
            "lang": "en"
        },
        {
            "id": "1467133506098806791",
            "public_metrics": {
                "retweet_count": 0,
                "reply_count": 0,
                "like_count": 0,
                "quote_count": 0
            },
            "created_at": "2021-12-04T14:07:40.000Z",
            "text": "Before the Cameras Even Roll, \u201cA Movie Lives or Dies by Casting\u201d https://t.co/JQcKkCJ2K6",
            "possibly_sensitive": false,
            "author_id": "1362177019",
            "lang": "en"
        },
        {
            "id": "1467133423961534466",
            "public_metrics": {
                "retweet_count": 2,
                "reply_count": 0,
                "like_count": 8,
                "quote_count": 0
            },
            "created_at": "2021-12-04T14:07:20.000Z",
            "text": "I would agree:\nhttps://t.co/2iOXGThB4q",
            "possibly_sensitive": false,
            "author_id": "950746018261463040",
            "lang": "en"
        },
        {
            "id": "1467133389669027843",
            "public_metrics": {
                "retweet_count": 0,
                "reply_count": 0,
                "like_count": 8,
                "quote_count": 0
            },
            "created_at": "2021-12-04T14:07:12.000Z",
            "text": "It\u2019s 8 am should I watch Dune",
            "possibly_sensitive": false,
            "author_id": "2429639750",
            "lang": "en"
        },
        {
            "id": "1467133298338058246",
            "public_metrics": {
                "retweet_count": 0,
                "reply_count": 0,
                "like_count": 2,
                "quote_count": 0
            },
            "created_at": "2021-12-04T14:06:50.000Z",
            "text": "Dune Peninsula 2021 12 02 19, my photograph on #Flickr https://t.co/eoTTjr8btg #Photography https://t.co/BV2LjMLlaQ",
            "possibly_sensitive": false,
            "author_id": "343119653",
            "lang": "en"
        },
        {
            "id": "1467133292923215883",
            "public_metrics": {
                "retweet_count": 0,
                "reply_count": 0,
                "like_count": 0,
                "quote_count": 0
            },
            "created_at": "2021-12-04T14:06:49.000Z",
            "text": "Dune Peninsula 2021 12 02 17, my photograph on #Flickr https://t.co/etagUAMf8J #Photography https://t.co/iuaSZqhuwy",
            "possibly_sensitive": false,
            "author_id": "343119653",
            "lang": "en"
        },
        {
            "id": "1467133006943035396",
            "public_metrics": {
                "retweet_count": 0,
                "reply_count": 0,
                "like_count": 0,
                "quote_count": 0
            },
            "created_at": "2021-12-04T14:05:41.000Z",
            "text": "The $Spice must flow !\n\ncome join @TheSpiceDAO and be a part of the future of Jodoroswky's DUNE\n\nhttps://t.co/eyGrk3wy7t",
            "possibly_sensitive": false,
            "author_id": "1399738664444440576",
            "lang": "en"
        },
        {
            "id": "1467132356486209538",
            "public_metrics": {
                "retweet_count": 115,
                "reply_count": 6,
                "like_count": 979,
                "quote_count": 47
            },
            "created_at": "2021-12-04T14:03:06.000Z",
            "text": "I can't get over it! \ud83e\udd75\u2764\ufe0f\n#TimotheeChalamet #dune #DuneMovie #london2021 https://t.co/U8gJdZ9N6a",
            "possibly_sensitive": false,
            "author_id": "1070101328846819328",
            "lang": "en"
        },
        {
            "id": "1467132342556844034",
            "public_metrics": {
                "retweet_count": 0,
                "reply_count": 0,
                "like_count": 3,
                "quote_count": 1
            },
            "created_at": "2021-12-04T14:03:03.000Z",
            "text": "I got to speak with my friend, Charles Williams (@gusterdubs), about Dune, literature that transcends genre, hope in heroes, and even \u201cunified consciousness.\u201d It was a typically fun and engaging conversation with Charles. Listen at https://t.co/YDjToNSv7S https://t.co/aMWQ1IavmG",
            "possibly_sensitive": false,
            "author_id": "259510313",
            "lang": "en"
        },
        {
            "id": "1467132206896193539",
            "public_metrics": {
                "retweet_count": 0,
                "reply_count": 0,
                "like_count": 0,
                "quote_count": 0
            },
            "created_at": "2021-12-04T14:02:30.000Z",
            "text": "Little secret we are ashkenazi like we give a fuck about you smelly dune coons , you made us drive an Uber with you Satanists pack in after a gang rape",
            "possibly_sensitive": false,
            "author_id": "1465020715657166848",
            "lang": "en"
        },
        {
            "id": "1467131804138315783",
            "public_metrics": {
                "retweet_count": 56,
                "reply_count": 22,
                "like_count": 368,
                "quote_count": 14
            },
            "created_at": "2021-12-04T14:00:54.000Z",
            "text": "Dune, but it\u2019s Nicholas Cage as Baron Harkonnen and everyone else is played by Muppets.",
            "possibly_sensitive": false,
            "author_id": "3390499229",
            "lang": "en"
        },
        {
            "id": "1467131675859689472",
            "public_metrics": {
                "retweet_count": 2,
                "reply_count": 1,
                "like_count": 3,
                "quote_count": 0
            },
            "created_at": "2021-12-04T14:00:24.000Z",
            "text": "Listening to @IanTheKiltmaker, @JDBuffington, and Chris of @_BadMovieNight discuss a month of DUNE ripoffs in the glorious month of Dunecember. #dune #fantasy #scifi #podcast https://t.co/nRzijiTjAw",
            "possibly_sensitive": true,
            "author_id": "3234099793",
            "lang": "en"
        },
        {
            "id": "1467131578623139843",
            "public_metrics": {
                "retweet_count": 0,
                "reply_count": 2,
                "like_count": 8,
                "quote_count": 0
            },
            "created_at": "2021-12-04T14:00:00.000Z",
            "text": "The House of Gucci filmmaker was set to direct a 1980s adaptation of the space epic, eventually picked up by David Lynch.\n\nhttps://t.co/MkU5izy3dh",
            "possibly_sensitive": false,
            "author_id": "15317676",
            "lang": "en"
        },
        {
            "id": "1467131578505744396",
            "public_metrics": {
                "retweet_count": 9,
                "reply_count": 1,
                "like_count": 63,
                "quote_count": 0
            },
            "created_at": "2021-12-04T14:00:00.000Z",
            "text": "Sandworms are a staple of sci-fi. But there are ecological and evolutionary limits to consider when deciding if a species like that featured in \"Dune\" could actually exist here on Earth. (From @novapbs) https://t.co/7EUrqvINCh",
            "possibly_sensitive": false,
            "author_id": "12133382",
            "lang": "en"
        },
        {
            "id": "1467131214855344136",
            "public_metrics": {
                "retweet_count": 28,
                "reply_count": 4,
                "like_count": 350,
                "quote_count": 1
            },
            "created_at": "2021-12-04T13:58:34.000Z",
            "text": "Standard shot VS IMAX 1.43:1 full aspect ratio. #DuneMovie https://t.co/tO9nVO1HPM",
            "possibly_sensitive": false,
            "author_id": "4464872069",
            "lang": "en"
        },
        {
            "id": "1467130990766305293",
            "public_metrics": {
                "retweet_count": 0,
                "reply_count": 0,
                "like_count": 0,
                "quote_count": 0
            },
            "created_at": "2021-12-04T13:57:40.000Z",
            "text": "Thank you Denis Villeneuve for saving cinema again. Dune is phenomenal.",
            "possibly_sensitive": false,
            "author_id": "1439851190083198976",
            "lang": "en"
        },
        {
            "id": "1467130317991399428",
            "public_metrics": {
                "retweet_count": 0,
                "reply_count": 0,
                "like_count": 0,
                "quote_count": 0
            },
            "created_at": "2021-12-04T13:55:00.000Z",
            "text": "Visit\n  Author Deanie Humphrys-Dunne https://t.co/DA9plrrtev \n\n#AuthorUpROAR @EarthDesires @DeanieHDunn\n\nCheck out this book - 'Charlene the Star and Hattie's Heroes' by Deanie Humphrys-Dunne, Holly Humphrys-Bajaj https://t.co/oWhZRGKWAt",
            "possibly_sensitive": false,
            "author_id": "318774557",
            "lang": "en"
        },
        {
            "id": "1467130075594305545",
            "public_metrics": {
                "retweet_count": 2,
                "reply_count": 3,
                "like_count": 9,
                "quote_count": 0
            },
            "created_at": "2021-12-04T13:54:02.000Z",
            "text": "I think about Dune a lot.",
            "possibly_sensitive": false,
            "author_id": "336944060",
            "lang": "en"
        },
        {
            "id": "1467129777152745474",
            "public_metrics": {
                "retweet_count": 5,
                "reply_count": 2,
                "like_count": 39,
                "quote_count": 0
            },
            "created_at": "2021-12-04T13:52:51.000Z",
            "text": "I had the opportunity to talk BattleTech, community building, and a bit of Dune with @BPLTEX on the latest episode of the Black Pants Legion podcast. Give it a listen here, https://t.co/cAxAZoLtOi",
            "possibly_sensitive": false,
            "author_id": "1278016263852371971",
            "lang": "en"
        },
        {
            "id": "1467129242517450764",
            "public_metrics": {
                "retweet_count": 0,
                "reply_count": 0,
                "like_count": 0,
                "quote_count": 0
            },
            "created_at": "2021-12-04T13:50:44.000Z",
            "text": "4 Reasons to Read The Dune Saga (No Spoilers) - YouTube https://t.co/npQjmPNcy3",
            "possibly_sensitive": false,
            "author_id": "1070798797150801920",
            "lang": "en"
        },
        {
            "id": "1467128314061983747",
            "public_metrics": {
                "retweet_count": 0,
                "reply_count": 0,
                "like_count": 10,
                "quote_count": 0
            },
            "created_at": "2021-12-04T13:47:02.000Z",
            "text": "guys i finally watched dune and OMG IM OBSESSED",
            "possibly_sensitive": false,
            "author_id": "1464469975545126916",
            "lang": "en"
        },
        {
            "id": "1467128097845968904",
            "public_metrics": {
                "retweet_count": 0,
                "reply_count": 0,
                "like_count": 0,
                "quote_count": 0
            },
            "created_at": "2021-12-04T13:46:11.000Z",
            "text": "1 of 5 stars to Children of Dune by Frank Herbert https://t.co/ZcMg74hyD8",
            "possibly_sensitive": false,
            "author_id": "56517509",
            "lang": "en"
        },
        {
            "id": "1467127698992496641",
            "public_metrics": {
                "retweet_count": 1,
                "reply_count": 1,
                "like_count": 1,
                "quote_count": 0
            },
            "created_at": "2021-12-04T13:44:36.000Z",
            "text": "Just saw Dune in imax and it was  the greatest experience I\u2019ve ever had at a movie. Holy shit. THIS WAS WORTH THE WAIT!!!  #Dune  #TimotheeChalamet  #DuneMovie https://t.co/YpuzriWGbG",
            "possibly_sensitive": false,
            "author_id": "213652415",
            "lang": "en"
        },
        {
            "id": "1467127634593136644",
            "public_metrics": {
                "retweet_count": 0,
                "reply_count": 1,
                "like_count": 1,
                "quote_count": 0
            },
            "created_at": "2021-12-04T13:44:20.000Z",
            "text": "\ud83c\udfa5 Dune (2021)\nloved the soundtrack + sound design\nsweet cinematography \nhaven\u2019t read the book yet so can\u2019t compare \ncertified hollywood kino\ndidn\u2019t like 1 casting choice\n\nTL;DR: soundtrack awesome every track a THX deep note\n\n7.5/10\n#MindOfBdonReviews #weregoingtobonniedune",
            "possibly_sensitive": false,
            "author_id": "30875571",
            "lang": "en"
        },
        {
            "id": "1467127595363930124",
            "public_metrics": {
                "retweet_count": 0,
                "reply_count": 0,
                "like_count": 6,
                "quote_count": 0
            },
            "created_at": "2021-12-04T13:44:11.000Z",
            "text": "Currently in the works and forthcoming in 2022: #War in #Film. #Semiotics #VisualSemiotics #WarFilms #FilmTwitter #MediaStudies #FilmStudies #Dune #Dunkirk #AlainDelon https://t.co/lfVnGcLSYq",
            "possibly_sensitive": false,
            "author_id": "1006023726",
            "lang": "en"
        },
        {
            "id": "1467127392837816330",
            "public_metrics": {
                "retweet_count": 0,
                "reply_count": 0,
                "like_count": 1,
                "quote_count": 0
            },
            "created_at": "2021-12-04T13:43:23.000Z",
            "text": "Sci-Fi Classics:\nStar Trek: A power plant.\nStar Wars: The army.\nDune: A business degree.\nDr. Who: Hunting the inbred.\nThe Matrix: Hunting film students.\n\nAny sci-fi film, to be a classic, has to be from the villain's perspective.",
            "possibly_sensitive": false,
            "author_id": "1392412021619109890",
            "lang": "en"
        },
        {
            "id": "1467127331441364992",
            "public_metrics": {
                "retweet_count": 0,
                "reply_count": 1,
                "like_count": 1,
                "quote_count": 0
            },
            "created_at": "2021-12-04T13:43:08.000Z",
            "text": "I haven't read Dune but if another space man brunette with nice hair betrays me IDK IF I CAN DO THIS ANYMORE. \ud83d\ude2d\ud83d\udc94",
            "possibly_sensitive": false,
            "author_id": "367237583",
            "lang": "en"
        },
        {
            "id": "1467127133940207619",
            "public_metrics": {
                "retweet_count": 0,
                "reply_count": 1,
                "like_count": 2,
                "quote_count": 0
            },
            "created_at": "2021-12-04T13:42:21.000Z",
            "text": "Another Ridleyism. Reasons he backed out of making a Dune movie.\n\n*Checks notes* Because Mexico smelled bad.\n\nGot it. https://t.co/1nJhXfEJ72",
            "possibly_sensitive": false,
            "author_id": "42105928",
            "lang": "en"
        },
        {
            "id": "1467127083537211399",
            "public_metrics": {
                "retweet_count": 0,
                "reply_count": 0,
                "like_count": 0,
                "quote_count": 0
            },
            "created_at": "2021-12-04T13:42:09.000Z",
            "text": "Marked as to-read: Dune by Frank Herbert https://t.co/peH9Ayglq6",
            "possibly_sensitive": false,
            "author_id": "1073573030499094528",
            "lang": "en"
        },
        {
            "id": "1467125803414601732",
            "public_metrics": {
                "retweet_count": 0,
                "reply_count": 1,
                "like_count": 0,
                "quote_count": 0
            },
            "created_at": "2021-12-04T13:37:04.000Z",
            "text": "watched dune and it honestly felt more like an episode of a tv show than a movie",
            "possibly_sensitive": false,
            "author_id": "989901528747134976",
            "lang": "en"
        },
        {
            "id": "1467125325272260610",
            "public_metrics": {
                "retweet_count": 0,
                "reply_count": 0,
                "like_count": 3,
                "quote_count": 0
            },
            "created_at": "2021-12-04T13:35:10.000Z",
            "text": "When the homies don't love dune as much as you do https://t.co/0DN0ApTdux",
            "possibly_sensitive": false,
            "author_id": "820836421699190785",
            "lang": "en"
        },
        {
            "id": "1467125018668584961",
            "public_metrics": {
                "retweet_count": 0,
                "reply_count": 0,
                "like_count": 0,
                "quote_count": 0
            },
            "created_at": "2021-12-04T13:33:56.000Z",
            "text": "Africa is Dune https://t.co/HLeWvzuqty",
            "possibly_sensitive": false,
            "author_id": "3294139659",
            "lang": "en"
        },
        {
            "id": "1467124867862609925",
            "public_metrics": {
                "retweet_count": 0,
                "reply_count": 0,
                "like_count": 0,
                "quote_count": 0
            },
            "created_at": "2021-12-04T13:33:21.000Z",
            "text": "exactly dune the best movie",
            "possibly_sensitive": false,
            "author_id": "806526372105555969",
            "lang": "en"
        },
        {
            "id": "1467124853912354819",
            "public_metrics": {
                "retweet_count": 0,
                "reply_count": 0,
                "like_count": 0,
                "quote_count": 0
            },
            "created_at": "2021-12-04T13:33:17.000Z",
            "text": "Erg Chebbi dunes by @YuriFAphoto - The photo was taken in Erg Chebbi, a famous dune in the moroccan side of the Sahara desert during the early morning, while the sun was rising on the opposite side.\n\nErg Chebbi - Merzouga - Morocco https://t.co/tfJX1lCIiW",
            "possibly_sensitive": false,
            "author_id": "2803096103",
            "lang": "en"
        },
        {
            "id": "1467124282778165251",
            "public_metrics": {
                "retweet_count": 0,
                "reply_count": 0,
                "like_count": 1,
                "quote_count": 0
            },
            "created_at": "2021-12-04T13:31:01.000Z",
            "text": "Lawrence of Arrakis: A Film Review of Dune Part 1 https://t.co/mxxLQXpDiu via @mygeekology",
            "possibly_sensitive": false,
            "author_id": "820979907429888003",
            "lang": "en"
        },
        {
            "id": "1467124081539563522",
            "public_metrics": {
                "retweet_count": 1,
                "reply_count": 0,
                "like_count": 6,
                "quote_count": 0
            },
            "created_at": "2021-12-04T13:30:13.000Z",
            "text": "Current #arcanejinx #Arcane progress! WIP before abs after! The pants had already been modded in the before pic. Still a fair bit to go but powering through so I can get back to my Dune stillsuit! \u2764\ufe0f #Jinx #JinxWasHere #LeagueOfLegends #LeagueOfLegendsFanArt #cosplayer https://t.co/08gbtgBYzN",
            "possibly_sensitive": false,
            "author_id": "273719222",
            "lang": "en"
        },
        {
            "id": "1467124015084965889",
            "public_metrics": {
                "retweet_count": 0,
                "reply_count": 0,
                "like_count": 0,
                "quote_count": 0
            },
            "created_at": "2021-12-04T13:29:57.000Z",
            "text": "booseoksoon\nmanifesting like the fear of an oven left on\rgod, I felt so much back then\ri was soft as a dune",
            "possibly_sensitive": false,
            "author_id": "1398422964421398535",
            "lang": "en"
        },
        {
            "id": "1467123925918404613",
            "public_metrics": {
                "retweet_count": 0,
                "reply_count": 0,
                "like_count": 0,
                "quote_count": 0
            },
            "created_at": "2021-12-04T13:29:36.000Z",
            "text": "Sahara desert by @YuriFAphoto - The photo was taken during the sunrise in this amazing piece of the Sahara desert, in the Moroccan side, this is the tallest dune of this part and it's called Erg Chebbi.\nMerzouga - Morocco https://t.co/jP0YuXLyWN",
            "possibly_sensitive": false,
            "author_id": "2803096103",
            "lang": "en"
        },
        {
            "id": "1467123843416219650",
            "public_metrics": {
                "retweet_count": 0,
                "reply_count": 1,
                "like_count": 1,
                "quote_count": 0
            },
            "created_at": "2021-12-04T13:29:16.000Z",
            "text": "SANSA BENE GESSERIT DUNE AU TASKED TO BED HER BROTHER JON ATREIDES!!!!!! SUSPECTED KWISATZ HADERACH!!!!!!!!!! SHAKING SCREAMING CUMMING CRYING ON THE SPOT",
            "possibly_sensitive": false,
            "author_id": "1091006017607917573",
            "lang": "en"
        },
        {
            "id": "1467123757806456832",
            "public_metrics": {
                "retweet_count": 1,
                "reply_count": 0,
                "like_count": 9,
                "quote_count": 0
            },
            "created_at": "2021-12-04T13:28:56.000Z",
            "text": "This man saw them using Thumpers in Dune for the Sandworms and decided he wanted to cosplay https://t.co/gHZHnGTlPb",
            "possibly_sensitive": false,
            "author_id": "1031293757759610880",
            "lang": "en"
        },
        {
            "id": "1467123613836926983",
            "public_metrics": {
                "retweet_count": 7,
                "reply_count": 13,
                "like_count": 76,
                "quote_count": 0
            },
            "created_at": "2021-12-04T13:28:22.000Z",
            "text": "my fav films of 2021\n\nPIG @MichaelSarnoski \n\nLAST NIGHT IN SOHO @edgarwright \n\nCENSOR @pranobaileybond \n\nNIGHTMARE ALLEY @RealGDT\n\nBELFAST @belfastmovie\n\nTITANE @TitaneMovie \n\nSPENCER @neonrated \n\nDUNE @dunemovie \n\nNO SUDDEN MOVE\n\nTHE LITTLE THINGS\n\nKID DETECTIVE\n\nGREEN KNIGHT https://t.co/YTR6MWyAEl",
            "possibly_sensitive": false,
            "author_id": "482523780",
            "lang": "en"
        },
        {
            "id": "1467123566965575680",
            "public_metrics": {
                "retweet_count": 0,
                "reply_count": 1,
                "like_count": 0,
                "quote_count": 0
            },
            "created_at": "2021-12-04T13:28:10.000Z",
            "text": "Just saw a YouTube video of a scene of Children of Dune, I didn't listen to the dialogue or anything but I might watch it because James McAvoy\nAlso he seems to spend a good chunk of the movie shirtless so that's a plus\nIt was really the height of his twink era",
            "possibly_sensitive": false,
            "author_id": "1283811985562402819",
            "lang": "en"
        },
        {
            "id": "1467123422534647809",
            "public_metrics": {
                "retweet_count": 0,
                "reply_count": 0,
                "like_count": 2,
                "quote_count": 0
            },
            "created_at": "2021-12-04T13:27:36.000Z",
            "text": "I'm sorry, I love sci fi and world building but Dune was pretty shit not gonna lie.\n\nDon't get the hype or the reviews to be honest, and that doesn't happen to me often! \n\nJust... The worst pacing, it needs to be a series like how HDM was fixed by being a series.",
            "possibly_sensitive": false,
            "author_id": "1000612897498656768",
            "lang": "en"
        },
        {
            "id": "1467123215436685312",
            "public_metrics": {
                "retweet_count": 0,
                "reply_count": 0,
                "like_count": 1,
                "quote_count": 0
            },
            "created_at": "2021-12-04T13:26:47.000Z",
            "text": "Shadout to all my Mapes in Australia that are watching @dunemovie this weekend!\n\n@Legendary @wbpictures #Dune #DuneMovie #ShadoutMapes",
            "possibly_sensitive": false,
            "author_id": "1174324529092382721",
            "lang": "en"
        },
        {
            "id": "1467123211632619521",
            "geo": {
                "place_id": "1d9a5370a355ab0c"
            },
            "public_metrics": {
                "retweet_count": 0,
                "reply_count": 0,
                "like_count": 1,
                "quote_count": 0
            },
            "created_at": "2021-12-04T13:26:46.000Z",
            "text": "How\u2019s your day starting out? #funQandA2021 @ryzemo #Dune #earlybirdgetstheworm https://t.co/wDKKT092IT",
            "possibly_sensitive": false,
            "author_id": "1482385172",
            "lang": "en"
        },
        {
            "id": "1467122723302244359",
            "public_metrics": {
                "retweet_count": 1,
                "reply_count": 19,
                "like_count": 236,
                "quote_count": 1
            },
            "created_at": "2021-12-04T13:24:49.000Z",
            "text": "#Dune is just spectacular. I can't remember the last time I came out of a film so in awe. https://t.co/j5npYzFXUv",
            "possibly_sensitive": false,
            "author_id": "21176417",
            "lang": "en"
        },
        {
            "id": "1467122433522028544",
            "public_metrics": {
                "retweet_count": 0,
                "reply_count": 1,
                "like_count": 6,
                "quote_count": 0
            },
            "created_at": "2021-12-04T13:23:40.000Z",
            "text": "Drew my boss at Secret Santa\n\nWanted to get him EN Dune but the local EN bookstore didn't have one\n\nBut they did have Hogfather which is a much better Christmas choice",
            "possibly_sensitive": false,
            "author_id": "2767148298",
            "lang": "en"
        },
        {
            "id": "1467121887897550848",
            "public_metrics": {
                "retweet_count": 0,
                "reply_count": 0,
                "like_count": 2,
                "quote_count": 0
            },
            "created_at": "2021-12-04T13:21:30.000Z",
            "text": "Quote your recent fav movie.\n\nMine : #Dune \nYours : ? https://t.co/i6jacfouud",
            "possibly_sensitive": false,
            "author_id": "1153647321223069697",
            "lang": "en"
        },
        {
            "id": "1467121704665116672",
            "public_metrics": {
                "retweet_count": 0,
                "reply_count": 0,
                "like_count": 1,
                "quote_count": 0
            },
            "created_at": "2021-12-04T13:20:46.000Z",
            "text": "DUNE IS SO SEXY",
            "possibly_sensitive": false,
            "author_id": "1101972607321038849",
            "lang": "en"
        },
        {
            "id": "1467121452541427713",
            "public_metrics": {
                "retweet_count": 0,
                "reply_count": 0,
                "like_count": 1,
                "quote_count": 0
            },
            "created_at": "2021-12-04T13:19:46.000Z",
            "text": "Played #DuneImperium today https://t.co/1lkZQDJDHU #bggplay",
            "possibly_sensitive": false,
            "author_id": "123188473",
            "lang": "en"
        },
        {
            "id": "1467121189420208128",
            "public_metrics": {
                "retweet_count": 0,
                "reply_count": 0,
                "like_count": 2,
                "quote_count": 0
            },
            "created_at": "2021-12-04T13:18:44.000Z",
            "text": "One of the best films of 2021. Yes, Dune was dynamic, but Finch is fantastic! https://t.co/nJkzOuH1Ry #Moviereview #Movies #films #writers #writing #writingservices #writerslift #writerscommunity #writingcommunity #bloggingcommunity #blogging #writersupportingwriters #Finch",
            "possibly_sensitive": false,
            "author_id": "2388565987",
            "lang": "en"
        },
        {
            "id": "1467121119790465026",
            "public_metrics": {
                "retweet_count": 3,
                "reply_count": 1,
                "like_count": 5,
                "quote_count": 0
            },
            "created_at": "2021-12-04T13:18:27.000Z",
            "text": "I\u2019m pretty sure this was supposed to get that #screenshotsaturday tag as well my friend #gamedev #indiedevs #indiegame #MadMax #rust #dune https://t.co/bW4YeLQBbd",
            "possibly_sensitive": false,
            "author_id": "1325911315940962306",
            "lang": "en"
        },
        {
            "id": "1467120758707130376",
            "public_metrics": {
                "retweet_count": 0,
                "reply_count": 2,
                "like_count": 3,
                "quote_count": 0
            },
            "created_at": "2021-12-04T13:17:01.000Z",
            "text": "someone behind me is talking about dune and saying it's too long and not great i'm taking this as a personal attack (also i'm still in queue for a ticket. i don't even know if there are some left and screening starts in 4 minutes)",
            "possibly_sensitive": false,
            "author_id": "1437081198698848261",
            "lang": "en"
        },
        {
            "id": "1467120320528076800",
            "public_metrics": {
                "retweet_count": 0,
                "reply_count": 0,
                "like_count": 5,
                "quote_count": 0
            },
            "created_at": "2021-12-04T13:15:16.000Z",
            "text": "why is Dune so loud - i think i broke my ears",
            "possibly_sensitive": false,
            "author_id": "1330141880034668560",
            "lang": "en"
        },
        {
            "id": "1467120264362151937",
            "public_metrics": {
                "retweet_count": 0,
                "reply_count": 0,
                "like_count": 0,
                "quote_count": 0
            },
            "created_at": "2021-12-04T13:15:03.000Z",
            "text": "Now playing Don&amp;#039;t Waste My Time by Cy Dune on WKNC.",
            "possibly_sensitive": false,
            "author_id": "1246833403",
            "lang": "en"
        },
        {
            "id": "1467120231885721605",
            "public_metrics": {
                "retweet_count": 0,
                "reply_count": 0,
                "like_count": 2,
                "quote_count": 0
            },
            "created_at": "2021-12-04T13:14:55.000Z",
            "text": "Let\u2019s talk abt Doja\u2019s woman mv parallels with Dune https://t.co/hs2gc49kMY",
            "possibly_sensitive": false,
            "author_id": "935771049907687424",
            "lang": "en"
        },
        {
            "id": "1467120089598148615",
            "public_metrics": {
                "retweet_count": 0,
                "reply_count": 0,
                "like_count": 6,
                "quote_count": 0
            },
            "created_at": "2021-12-04T13:14:21.000Z",
            "text": "Pics from the new Dune: Part II trailer https://t.co/G0oRhmGp7S",
            "possibly_sensitive": false,
            "author_id": "1099303934156591105",
            "lang": "en"
        },
        {
            "id": "1467119990759432192",
            "public_metrics": {
                "retweet_count": 0,
                "reply_count": 0,
                "like_count": 1,
                "quote_count": 0
            },
            "created_at": "2021-12-04T13:13:58.000Z",
            "text": "I tried watching Dune and yeah\u2026 \ud83d\ude41",
            "possibly_sensitive": false,
            "author_id": "1257641446846455809",
            "lang": "en"
        },
        {
            "id": "1467119748341243906",
            "geo": {
                "place_id": "00b673715a35dfa7"
            },
            "public_metrics": {
                "retweet_count": 0,
                "reply_count": 0,
                "like_count": 4,
                "quote_count": 0
            },
            "created_at": "2021-12-04T13:13:00.000Z",
            "text": "Can\u2019t stop thinking about #Dune tbh.",
            "possibly_sensitive": false,
            "author_id": "1401107881",
            "lang": "en"
        },
        {
            "id": "1467119510109196288",
            "public_metrics": {
                "retweet_count": 0,
                "reply_count": 0,
                "like_count": 1,
                "quote_count": 0
            },
            "created_at": "2021-12-04T13:12:03.000Z",
            "text": "Dec. 4,2021\uff08Sat.\uff09\u2614\ufe0frainy\nToday my son and I visited the Tottori Sand Dunes. It is important to actually see the real thing. We also had a real taste of Kodoku-no-gourmet. #Dune https://t.co/QrGQwsZKIA",
            "possibly_sensitive": false,
            "author_id": "1315371880140816385",
            "lang": "en"
        },
        {
            "id": "1467119244550631425",
            "public_metrics": {
                "retweet_count": 0,
                "reply_count": 2,
                "like_count": 37,
                "quote_count": 0
            },
            "created_at": "2021-12-04T13:11:00.000Z",
            "text": "\ud83c\udfac: Watching #Dune Part One on Blu-ray \ud83d\udcc0 https://t.co/yxExXF0fuQ",
            "possibly_sensitive": false,
            "author_id": "1703825978",
            "lang": "en"
        },
        {
            "id": "1467119174572933122",
            "public_metrics": {
                "retweet_count": 0,
                "reply_count": 4,
                "like_count": 20,
                "quote_count": 2
            },
            "created_at": "2021-12-04T13:10:43.000Z",
            "text": "Dune easily one of the best hyper cinematic movies I\u2019ve seen in ages, also the sound design was incredible",
            "possibly_sensitive": false,
            "author_id": "2466915001",
            "lang": "en"
        },
        {
            "id": "1467119142667014158",
            "public_metrics": {
                "retweet_count": 2,
                "reply_count": 3,
                "like_count": 25,
                "quote_count": 1
            },
            "created_at": "2021-12-04T13:10:36.000Z",
            "text": "A very short guide for the  new Dune-fans!\n(Found it on Reddit)\nHave a nice weekend even if anybody has to work!\n#dune #dunemovie https://t.co/6ZtykSEWgs",
            "possibly_sensitive": false,
            "author_id": "1006126183954644992",
            "lang": "en"
        },
        {
            "id": "1467119003407585281",
            "geo": {
                "place_id": "004ec16c62325149"
            },
            "public_metrics": {
                "retweet_count": 1,
                "reply_count": 1,
                "like_count": 1,
                "quote_count": 0
            },
            "created_at": "2021-12-04T13:10:02.000Z",
            "text": "StarWars vs StarTrek seems like such a silly argument after seeing Dune.",
            "possibly_sensitive": false,
            "author_id": "149041424",
            "lang": "en"
        },
        {
            "id": "1467118908960247814",
            "public_metrics": {
                "retweet_count": 0,
                "reply_count": 2,
                "like_count": 4,
                "quote_count": 0
            },
            "created_at": "2021-12-04T13:09:40.000Z",
            "text": "Just watched #Dune &amp; damn, how tf is so Timothee pretty &amp; hot? I knew I liked skinny boys but AHHHHHHHH",
            "possibly_sensitive": false,
            "author_id": "1363533250073780226",
            "lang": "en"
        },
        {
            "id": "1467118496098054145",
            "public_metrics": {
                "retweet_count": 0,
                "reply_count": 0,
                "like_count": 0,
                "quote_count": 0
            },
            "created_at": "2021-12-04T13:08:01.000Z",
            "text": "Someone needs to make a fan cam of the baron in dune",
            "possibly_sensitive": false,
            "author_id": "88119674",
            "lang": "en"
        },
        {
            "id": "1467118367370723330",
            "public_metrics": {
                "retweet_count": 0,
                "reply_count": 0,
                "like_count": 0,
                "quote_count": 0
            },
            "created_at": "2021-12-04T13:07:31.000Z",
            "text": "Saw #DuneMovie tonight and damn was it good! Momoa is great and Skarsg\u00e5rd is utterly disgusting as the Baron. Makes me appreciate the book even more #Dune",
            "possibly_sensitive": false,
            "author_id": "257300217",
            "lang": "en"
        },
        {
            "id": "1467118349633081361",
            "public_metrics": {
                "retweet_count": 0,
                "reply_count": 1,
                "like_count": 2,
                "quote_count": 0
            },
            "created_at": "2021-12-04T13:07:26.000Z",
            "text": "Finally saw Dune the way Denis Villeneuve intended last night. In my home with the dishwasher running next to the tv. Why them aliens gotta whisper the whole time?",
            "possibly_sensitive": false,
            "author_id": "269902741",
            "lang": "en"
        },
        {
            "id": "1467118235564879875",
            "public_metrics": {
                "retweet_count": 0,
                "reply_count": 2,
                "like_count": 3,
                "quote_count": 0
            },
            "created_at": "2021-12-04T13:06:59.000Z",
            "text": "Prepping for our second session of the Dune RPG tonight. This is a very different GMing experience than any other game I've run.",
            "possibly_sensitive": false,
            "author_id": "1488477762",
            "lang": "en"
        },
        {
            "id": "1467118132334510080",
            "public_metrics": {
                "retweet_count": 0,
                "reply_count": 1,
                "like_count": 0,
                "quote_count": 0
            },
            "created_at": "2021-12-04T13:06:35.000Z",
            "text": "Remember that one writer who got dragged for saying \"fuck all y'all arguing dune was a good movie\", in reference to petty arguments about how good an adaptation it was\n\nAnd then got dragged by all of twitter because the discourse was actually about something bigger",
            "possibly_sensitive": false,
            "author_id": "1008195009852555264",
            "lang": "en"
        },
        {
            "id": "1467117862888169475",
            "public_metrics": {
                "retweet_count": 0,
                "reply_count": 0,
                "like_count": 0,
                "quote_count": 0
            },
            "created_at": "2021-12-04T13:05:30.000Z",
            "text": "Opinion | Humanity needs big plans. \u2018Dune\u2019 and \u2018Foundation\u2019 show how hard it is to make them. https://t.co/lGYg5itbbv via @instapaper",
            "possibly_sensitive": false,
            "author_id": "3315611",
            "lang": "en"
        },
        {
            "id": "1467117784119140353",
            "public_metrics": {
                "retweet_count": 1,
                "reply_count": 3,
                "like_count": 16,
                "quote_count": 0
            },
            "created_at": "2021-12-04T13:05:12.000Z",
            "text": "I had the depressing thought some people who watch Dune will call it \u201cwoke sjw garbage\u201d\n\nI can\u2019t imagine how fucked your mind has to be to not be able to enjoy art",
            "possibly_sensitive": false,
            "author_id": "1281920742",
            "lang": "en"
        },
        {
            "id": "1467117754197106696",
            "public_metrics": {
                "retweet_count": 0,
                "reply_count": 0,
                "like_count": 1,
                "quote_count": 0
            },
            "created_at": "2021-12-04T13:05:04.000Z",
            "text": "#NowPlaying Herman Dune - On A Saturday\n\nsur https://t.co/kQBnAIKwBX\n\n#100AnsDeLaRadio #webradio https://t.co/qfn4mPXaYR",
            "possibly_sensitive": false,
            "author_id": "1413034238027436034",
            "lang": "en"
        },
        {
            "id": "1467117544729423875",
            "public_metrics": {
                "retweet_count": 0,
                "reply_count": 1,
                "like_count": 9,
                "quote_count": 0
            },
            "created_at": "2021-12-04T13:04:15.000Z",
            "text": "Dune https://t.co/VaOEmiGm0g",
            "possibly_sensitive": false,
            "author_id": "1409045802002100224",
            "lang": "en"
        },
        {
            "id": "1467117264801464325",
            "public_metrics": {
                "retweet_count": 0,
                "reply_count": 1,
                "like_count": 19,
                "quote_count": 0
            },
            "created_at": "2021-12-04T13:03:08.000Z",
            "text": "Saw DUNE. \n\nThe best movie of 2021 easily",
            "possibly_sensitive": false,
            "author_id": "1281920742",
            "lang": "en"
        },
        {
            "id": "1467117243519709184",
            "public_metrics": {
                "retweet_count": 0,
                "reply_count": 0,
                "like_count": 9,
                "quote_count": 0
            },
            "created_at": "2021-12-04T13:03:03.000Z",
            "text": "I have noodles and painkillers and the possibility of a new genvy.\n\n#NowWatching DUNE (1984) https://t.co/W67jiorlrc",
            "possibly_sensitive": false,
            "author_id": "1282989211398868997",
            "lang": "en"
        },
        {
            "id": "1467117215665168394",
            "public_metrics": {
                "retweet_count": 2,
                "reply_count": 1,
                "like_count": 11,
                "quote_count": 0
            },
            "created_at": "2021-12-04T13:02:56.000Z",
            "text": "\u201cI must not fear. Fear is the mind killer.\u201d\n\nLitany of Fear - Dune.",
            "possibly_sensitive": false,
            "author_id": "21156407",
            "lang": "en"
        }
    ],
    "meta": {
        "newest_id": "1467138693550989314",
        "oldest_id": "1467117215665168394",
        "result_count": 99,
        "next_token": "b26v89c19zqg8o3fpdy8ibc6c9w3tahcj3xjhyms5pmrh"
    }
}